loap/__init__.py
loap/loap.py
loap/tests/__init__.py
loap/tests/test_loap.py
loap-0.2.3.dist-info/METADATA
loap-0.2.3.dist-info/WHEEL
loap-0.2.3.dist-info/top_level.txt
loap-0.2.3.dist-info/RECORD
